OpenPluginApi/ApiTemplates.py
OpenPluginApi/PluginLoader.py
OpenPluginApi/Schedule.py
OpenPluginApi/__init__.py
OpenPluginApi/async/PluginLoader.py
OpenPluginApi/async/__init__.py
OpenPluginApi/asyncSupport/PluginLoader.py
OpenPluginApi/asyncSupport/__init__.py
OpenPluginApi-1.1.1.dist-info/METADATA
OpenPluginApi-1.1.1.dist-info/WHEEL
OpenPluginApi-1.1.1.dist-info/top_level.txt
OpenPluginApi-1.1.1.dist-info/RECORD
