Metadata-Version: 2.1
Name: OpenPluginApi
Version: 1.1.1
Summary: Allows you to easily create a full plugin system for your project.
Home-page: https://github.com/spidertyler2005/openPluginApi
Author: Benjamin Tyler Austin Jr
Author-email: BTAustin1122@gmail.com
License: MIT
Keywords: OPA,Plugin,PluginApi,Plugin Api Creator,Open Plugin Api
Platform: UNKNOWN
Classifier: Development Status :: 5 - Production/Stable
Classifier: Intended Audience :: Developers
Classifier: Topic :: Software Development :: Build Tools
Classifier: License :: OSI Approved :: MIT License
Classifier: Programming Language :: Python :: 3
Classifier: Programming Language :: Python :: 3.6
Classifier: Programming Language :: Python :: 3.7
Classifier: Programming Language :: Python :: 3.8
Requires-Python: >=3.6
